{
  "doc_id": "보도자료_85029",
  "source": "fsc_crawler",
  "title": "[보도자료] 금융권 침해사고가 재발하지 않도록 철저히 대비하고 점검하겠습니다",
  "category": "금융위/보도자료",
  "doc_type": "보도자료",
  "text": "제목: [보도자료] 금융권 침해사고가 재발하지 않도록 철저히 대비하고 점검하겠습니다\n\n금융권 \n침해사고가 재발하지 않도록\n \n철저히 대비\n하고 \n점검\n하겠습니다.\n\n - \n대담하고 치밀\n해진 \n최신 해킹 추세\n에 비추어 \n외부 접속 인프라\n, \n백업장비\n 등 관련 \n침해사고\n \n대비태세 강화\n 주문 -\n\n \n\n- \n유사사고 재발방지를 위한 후속조치 시행\n -\n\n① \n全 금융권\n 대상 \n랜섬웨어 등 \n침해사고 \n대비태세 자체점검\n 실시\n\n② 백업체계 등 대비태세 중점 \n테마검사\n 및 \n블라인드 모의해킹\n 실시\n\n③ \n보안사고\n 발생시 \n징벌적 과징금 부과\n 등\n 제도개선\n 방안 마련\n\nⅠ. 회의개요\n \n\n  \n금융위원회\n는 ’25.7.30.(수), \n｢금융권ㆍ금융 공공기관 침해사고 대비태세 점검회의｣를 개최\n하였다. 이번 회의는 지난 14일 \nSGI서울보증 랜섬웨어 \n사고\n를 계기로 \n금융권 및 금융 공공기관\n의 랜섬웨어 등 \n침해사고 대비태세를\n 점검\n하고 \n현장의 의견을 청취\n하여 침해사고 예방을 위한 \n조치사항 등을 논의\n하기 위해 개최되었다.\n\n▪ 일시/장소\n : ‘25.7.30.(수) 10:30\n / \n금융위원회 대회의실\n(정부서울청사 16층)\n \n\n \n \n\n▪ \n참석자\n \n\n   (금융위) 디지털금융정책관\n(주재)\n, 금융안전과, 보험과\n \n\n   (금융공공기관등) SGI서울보증, 주택금융공사, 서민금융진흥원, 신용회복위원회, 금융결제원, 신용정보원\n \n\n   (협회) 은행연합회, 생명보험협회, 손해보험협회, 금융투자협회, 여신금융협회, 핀테크산업협회\n \n\n   (유관기관) 금융감독원\n IT검사국장, 금융보안원 사이버대응본부장\n \n\nⅡ. 주요 논의사항 및 후속조치\n \n\n  \n금\n융위원회 \n디지털금융정책관\n은 모두 발언에서 “최근 IT 기술 발전 등에\n \n따라 \n해킹 수범이 대담하고 치밀\n해지고 있어, 대형 IT 기업 뿐 아니라\n \nSGI 서울보증 등 \n금융회사에까지 침해사고가 발생\n하는 상황”임을 언급\n하면서 “금융권에 더 이상 \n유사한 침해사고가 발생하지 않도록\n 금융권\n 관계자들 \n모두 높은 경각심을 가지고 대비\n할 필요가 있다”고 강조하였다.\n\n  또한, “\nSGI 사례에서 보듯이 금융회사의 경우 작은 보안 실수\n만으로도  \n걷잡을 수 없이 \n큰 소비자 불편을 초래\n할 수 있으며, 이는 \n금융 신뢰성\n과도\n \n연관되어 있는 만큼 \n금융안전\n에 있어서는 \n과하다고 생각될 정도\n로 \n빈틈없이 \n점검하고 보완\n하여야 한다”고 당부하였다.\n\n❶ 점검회의 참석자의 주요 발언내용\n\n  \nSGI 서울보증\n은 현재까지의 랜섬웨어 \n침해사고 경과 및 대응 현황\n에\n 대하여 설명하면서, \n금융보안원\n의 신속한 \n랜섬웨어 복호화 지원\n에 힘입어 지난 \n7.21일 서버가 모두 복구\n되어 \n대고객 업무가 완전 정상화 \n되었다고 강조하였다. 침해사고 원인에 대해서는 정밀 조사가 진행중이며 \n외부접속 \n인프라 관리\n 등 \n보안 관리 체계 전반\n에 대한 \n보완 조치를 진행\n하고 있다고\n 밝혔다.\n\n  사고 이후 \n소비자 피해 최소화\n를 위해 \n‘\n선대출\n 후보증\n’ 등을 통해 대응\n하였으며, \n피해신고센터\n를 운영하여 접수된 소비자 \n피해에 대한 보상을\n \n진행\n하고 있다고 설명하였다. “향후 관련 \n매뉴얼을 고도화\n하여 유사 사고시\n \n보다 신속히 대응\n할 수 있도록 하겠다”고 강조하면서 발언을 마무리하였다.\n\n  \n금융감독원\n은 “’25.2분기부터 \n외부접속 인프라의 보안 취약점\n을 악용한 침해사고가 증가하고 있다”는 점을 언급하면서, 그간 “\n전 금융권\n에\n 보안 \n강화 유의사항을 전파\n”하는 등 침해사고 예방을 위해 적극적으로 대응하여\n 왔다고 밝혔다.\n\n  \n특히, “\nSGI 서울보증 침해사고 이후 2차례\n 전 금융권에 \n유의사항을\n 긴급 전파\n한 만큼 향후 전 금융권을 대상으로 \n자체점검을 실시\n하고, 해당 \n점검결과를 바탕으로 \n현장점검\n 및 \n검사를 실시\n하여 유사한 사고가 \n금융권\n에서\n 재발하지 않도록 만전\n을 기하겠다”고 강조하였다.\n\n  \n금융보안원\n은 금번 침해사고 조사ㆍ분석 과정에서 확인된 \n사고발생 원인\n과\n \n랜섬웨어 분석\n을 통한 \n데이터 복구 과정\n을 설명하면서, “다행히도 \n금번\n 사고\n의 경우 \n복호화에 성공\n하여 \n데이터를 손실없이 신속하게 복구\n할 수 \n있었지만, 이는 \n매우 드문 경우\n로서 랜섬웨어 사고에 대비하여 \n실효성 있는\n 백업ㆍ복구\n \n정책을 마련\n하여 이행하여야 한다”고 강조하였다.\n\n  \n또한, “\nVPN 등 외부에서 접근 가능한 시스템\n에 대한 취약점을 \n주기적으로\n 점검\n하여 제거하고,\n 불필요한 네트워크 서비스 포트는 원천 차단\n할 필요가 있다”고 참석한 금융권 관계자들에게 당부하였다.\n\n  각 \n공공기관\n은 랜섬웨어 등 침해사고 대비현황을 설명하면서 최근 여러 \n분야에서 보안사고 발생이 증가하는 만큼 금융 공공기관에서는 침해사고가\n 발생하지 않도록 더 \n세심하고 철저하게 대비\n하고 있다고 밝혔다.\n\n  각 금융협회는 소비자가 안심하고 전자금융서비스를 이용할 수 있도록 각 금융회사에 \n대비태세\n를 철저히 하도록 \n안내\n하는 한편 \n협회차원\n에서도 \n회원사 대상 보안강화 관련 \n정보공유 및 간담회\n를 \n개최\n하는 등 \n각 금융회사가\n 보안체계\n를 \n고도화\n할 수 있도록\n 지원\n하겠다고 설명하였다.\n\n❷ 침해사고 예방을 위한 후속조치\n\n  \n금융위원회와 금융감독원은 회의에서 금융권 침해사고가 재발하지 않도록\n \n정부차원에서 \n금융권 보안강화를 위한 후속조치를 추진\n하겠다고 발표하였다.\n\n ① 우선, 전자금융서비스를 제공하는 금융 공공기관, 금융회사, 전자금융\n업자를 대상으로 \n랜섬웨어 등 침해사고 대비태세\n에 대한 \n자체점검을 실시\n할\n 예정이다.\n\n  7월중 각 금융회사 및 금융 공공기관에 자체점검표를 배포하여 \n8월까지 \n자체점검 및 보완\n토록 조치하는 한편 각 기관의 \n점검결과를 취합하고\n 분석\n하여 필요시 금융회사등이 \n보안강화 조치\n를 취할 수 있도록 \n안내 및 지원\n할 계획이다.\n\n ② 금감원은 위 자체점검 결과 등을 참고하여 \n9월부터 금융회사를 직접 점검\n할 예정이다. 특히, 최근 피해사례가 증가하는\n 랜섬웨어에 대한 대응체계\n와 \n전산장애 발생시 복구를 위한 백업현황\n 등을 \n중점적으로 점검\n하여 유사사고에 대한 대비태세가 갖추어져 있는지 확인할 계획이다.\n\n ③ \n금감원ㆍ금보원\n 합동으로 전 금융권을 대상으로 9월부터 \n블라인드 모의\n 해킹\n*\n도 실시\n할 예정이다. 모의 해킹을 통해 각 금융회사의 \n해킹에 대한 \n방어체계가 잘 동작\n하는지, \n보완할 점\n은 무엇인지 확인하여 금융회사가 \n보안\n수준을 강화\n할 수 있도록 \n지원\n할 계획이다.\n\n  * \n해킹 시도 일시\n 및 대상 금융회사를 사전에 알리지 않고 불시에 해킹 시도\n\n ④ 위 금융권 \n단기 보안 확보 조치와 병행\n하여, 금융회사가 적극적으로 보안 역량을 강화하고 침해사고 대비태세를 구축해 나갈 수 있는 \n제도적 \n개선방안도 검토\n해 나갈 예정이다.\n\n  \n▲ 보안체계 미흡으로 중대한 \n보안사고 발생시 징벌적 과징금 부과\n,\n \n▲ CISO가 주도적으로 보안강화를 할 수 있도록 \nCISO의 권한 강화\n,\n ▲ 금융권 침해 위협정보를 체계적으로 관리ㆍ전파하는 “\n통합관제시스템\n”의 \n조속한 구축\n 등을 추진할 계획이다.\n\n  \n아울러, 소비자 피해 방지를 위해 ▲ 보안사고 발생시 \n사고시점ㆍ내용ㆍ\n소비자 유의사항\n 등을\n 외부에 투명하게 공개\n하도록 하고, ▲ 소비자가\n \n금융회사별 \n보안 수준을 비교하고 서비스를 선택\n할 수 있도록 \n공시를\n 강화\n하며, ▲ 금융회사가 전산사고로\n 업무 중단시 신속한 우회 서비스와 소비자 피해 보상\n이 이루어지도록 \n금융회사별 대응 매뉴얼\n도 갖추도록 할 계획이다.\n\n첨부파일 (3)\n첨부파일 목록\n\n250730(보도자료) 금융권 침해사고가 재발하지 않도록 철저히 대비하고 점검하겠습니다.pdf\n\n (319 KB) \n\n파일뷰어\n\n파일다운로드\n\n250730(보도자료) 금융권 침해사고가 재발하지 않도록 철저히 대비하고 점검하겠습니다.hwp\n\n (188 KB) \n\n파일다운로드\n\n250730(보도자료) 금융권 침해사고가 재발하지 않도록 철저히 대비하고 점검하겠습니다.hwpx\n\n (201 KB) \n\n파일다운로드\n\n목록으로",
  "version_date": "2025-07-30",
  "related_laws": [],
  "collected_at": "2026-05-22",
  "question": "",
  "answer": "",
  "url": ""
}