{
  "doc_id": "법령해석_2866",
  "source": "fsc_crawler",
  "title": "자본시장법 제60조에 따른 자료의 기록·유지 방법 검토 요청",
  "category": "공통",
  "doc_type": "법령해석",
  "text": "질의요지:\n□ \n자본시장법 시행령 제\n62\n조 제\n1\n항 각 호 문서 원본을 폐기하고 스캔파일 형태로\n \n보관할 수 있는지\n\n회답:\n□ \n자본시장법 시행령 제\n62\n조제\n1\n항제\n5\n호 뿐만 아니라\n, \n제\n1\n호부터 제\n4\n호\n까지의\n \n문서들도 \n‘\n서면\n, \n전산자료\n, \n마이크로필름\n’\n으로 보관 가능합니다\n.\n\n이유:\n□ \n금융투자업규정 제\n4-13\n조는 자본시장법 시행령 제\n62\n조제\n1\n항제\n5\n호에 \n따라\n \n별표 \n12\n에서 정한 최소 보존기간 이상의 자료 보관방법을 서면\n,\n \n전산자료\n, \n마이크로필름으로 규정하고 있으며\n, \n\n \n\nㅇ \n별표 \n12\n에서는 비단 자본시장법 시행령 제\n62\n조제\n1\n항제\n5\n호 뿐만 아니라\n,\n \n같은 항 제\n1\n호부터 제\n4\n호까지의 자료를 망라하여 최소 보존기간을 규정하고 있어\n, \n사실상 같은 항 제\n1\n호부터 제\n5\n호까지의 자료 모두를 \n‘\n서면\n, \n전산자료\n, \n마이크로필름\n’ \n형태로 기록\n‧\n유지할 수 있습니다\n.",
  "version_date": "2020-03-31",
  "related_laws": [],
  "collected_at": "2026-05-22",
  "question": "□ \n자본시장법 시행령 제\n62\n조 제\n1\n항 각 호 문서 원본을 폐기하고 스캔파일 형태로\n \n보관할 수 있는지",
  "answer": "□ \n자본시장법 시행령 제\n62\n조제\n1\n항제\n5\n호 뿐만 아니라\n, \n제\n1\n호부터 제\n4\n호\n까지의\n \n문서들도 \n‘\n서면\n, \n전산자료\n, \n마이크로필름\n’\n으로 보관 가능합니다\n.",
  "url": ""
}