{
  "doc_id": "법령해석_4040",
  "source": "fsc_crawler",
  "title": "주택법상 지역주택조합에 대한 연대보증 입보 가능 여부",
  "category": "기타",
  "doc_type": "법령해석",
  "text": "문서번호: 220174\n\n질의요지:\n차주가 도시정비법 상 재건축조합 또는 주택법상 지역주택조합인 경우의 프로젝트금융에서 시공사의 연대보증이 가능한지\n?\n\n회답:\n금융소비자보호법 제\n20\n조제\n1\n항제\n4\n호다목은 금융상품판매업자등이 우월적 지위를 이용하여 금융소비자의 권익을 침해하는 행위로서 대출상품의 계약과 관련하여 \n제\n3\n자의 연대보증을 요구하는 행위를 원칙적으로 금지\n하고\n, \n동법 \n시행령 및 감독규정에 열거된 예외적인 경우\n에만 \n연대보증을 허용\n하고 있습니다\n.\n\n  \n\n구체적으로 \n시행령 제\n15\n조제\n2\n항제\n2\n호 단서\n \n및 \n감독규정 제\n14\n조제\n1\n항제\n2\n호\n에 따르면\n \n법인인 금융소비자에 대한 대출시\n,\n「\n자본시장과 금융투자업에 관한 법률\n」\n에 따른 프로젝트금융\n(\n대출로 한정한다\n) \n또는 이와 유사한 구조의 금융상품에 관한 계약을 \n체결하는 경우에 그 \n프로젝트금융의 대상이 되는 사업에 따른 이익을 금융소비자와\n \n공유하는 법인의 경우에는 연대보증이 허용됩니다\n.\n\n  \n\n｢\n도시 및 주거환경정비법\n｣\n에 따른 재개발\nㆍ\n재건축 조합\n은 \n근거 법률에 따라 법인격이\n \n인정\n되므로\n, \n｢\n금융소비자보호법\n｣\n상 \n법인인 금융소비자\n에 해당합니다\n.\n\n  \n\n다만\n, \n｢\n주택법\n｣ \n상 지역주택조합\n은 근거법 상\n \n법인격을 인정하는 조항이 없으므로\n \n법인인 금융소비자로 볼 수 없을 것입니다\n.\n\n이유:\n회답과 동일",
  "summary_text": "",
  "attachments": [],
  "version_date": "2022-08-03",
  "related_laws": [],
  "collected_at": "2026-05-22",
  "question": "차주가 도시정비법 상 재건축조합 또는 주택법상 지역주택조합인 경우의 프로젝트금융에서 시공사의 연대보증이 가능한지\n?",
  "answer": "금융소비자보호법 제\n20\n조제\n1\n항제\n4\n호다목은 금융상품판매업자등이 우월적 지위를 이용하여 금융소비자의 권익을 침해하는 행위로서 대출상품의 계약과 관련하여 \n제\n3\n자의 연대보증을 요구하는 행위를 원칙적으로 금지\n하고\n, \n동법 \n시행령 및 감독규정에 열거된 예외적인 경우\n에만 \n연대보증을 허용\n하고 있습니다\n.\n\n  \n\n구체적으로 \n시행령 제\n15\n조제\n2\n항제\n2\n호 단서\n \n및 \n감독규정 제\n14\n조제\n1\n항제\n2\n호\n에 따르면\n \n법인인 금융소비자에 대한 대출시\n,\n「\n자본시장과 금융투자업에 관한 법률\n」\n에 따른 프로젝트금융\n(\n대출로 한정한다\n) \n또는 이와 유사한 구조의 금융상품에 관한 계약을 \n체결하는 경우에 그 \n프로젝트금융의 대상이 되는 사업에 따른 이익을 금융소비자와\n \n공유하는 법인의 경우에는 연대보증이 허용됩니다\n.\n\n  \n\n｢\n도시 및 주거환경정비법\n｣\n에 따른 재개발\nㆍ\n재건축 조합\n은 \n근거 법률에 따라 법인격이\n \n인정\n되므로\n, \n｢\n금융소비자보호법\n｣\n상 \n법인인 금융소비자\n에 해당합니다\n.\n\n  \n\n다만\n, \n｢\n주택법\n｣ \n상 지역주택조합\n은 근거법 상\n \n법인격을 인정하는 조항이 없으므로\n \n법인인 금융소비자로 볼 수 없을 것입니다\n.",
  "document_number": "220174",
  "external_id": "4040",
  "url": "",
  "metadata": {
    "fsc_idx": "4040",
    "document_number": "220174",
    "gubun": "법령해석",
    "list_title": "주택법상 지역주택조합에 대한 연대보증 입보 가능 여부",
    "list_category": "",
    "reg_date": "2022.08.03"
  }
}