{
  "doc_id": "fss_행정지도_20200824162708913",
  "source": "fss_crawler",
  "title": "P2P대출 가이드라인 기간 연장 및 일부 개정",
  "category": "금융감독원/행정지도내역",
  "doc_type": "행정지도내역",
  "text": "제목: P2P대출 가이드라인 기간 연장 및 일부 개정\n\n제목 \n\nP2P대출 가이드라인 기간 연장 및 일부 개정\n\n관리번호 \n\n행2017-21001\n\n문서번호 \n\nP2P감독팀-63\n\n시행일 \n\n20200827\n\n유효기간 \n\n\r\n\t\t\t\t\t20210827\r\n\t\t\t\t\n\n시행여부 \n\n\r\n\t\t\t\t\t\r\n\t\t\t\t\t\r\n\t\t\t\t\t폐지\r\n\t\t\t\t\t\r\n\t\t\t\t\n\n첨부파일 \n\nP2P대출 가이드라인_Fn_첨부용.hwp\n\n\r\n\t\t\t\t\r\n\t\t\t\t “이 행정지도는 금융행정의 목적을 달성하기 위하여 귀 기관에 자발적인 협조를 요청하는 것으로서, 금융당국은 이 행정지도를 준수하지 않았다는 이유만으로 귀 기관에 불이익한 조치를 하지 않습니다.”\r\n \n \n       1. 관련근거\r\n            -「금융규제 운영규정」제8조\r\n \n       2. 「온라인투자연계금융업 및 이용자 보호에 관한 법률」(이하 ‘P2P법’)이 ’20.8.27. 시행될 예정이나, 법 시행 전 P2P업을 영위하는 업체들에 대해서는 1년간 등록 유예기간이 부여되며 해당 기간 동안에는 「P2P대출 가이드라인」을 적용받게 됩니다. \r\n \n        3. 이에 따라 등록 유예기간 동안 ‘P2P법에 따라 등록한 온라인투자연계금융업자’와 ‘미등록 P2P업체’ 사이의 규제 차익이 발생할 수 있으며, 이로 인한 이용자 보호 문제 등을 감안하여 P2P법령에서 규정한 다양한 이용자 보호 장치들을 「P2P대출 가이드라인」에 포함할 필요가 있습니다. \r\n \n        4. 이에 「P2P대출 가이드라인」행정지도 내용을 개정하고 아래와 같이 가이드라인 유효기간을 ‘21.8.26.까지 추가 연장하오니, 관련업무 수행에 만전을 기하여 주시기 바랍니다.\r\n \n \n \n            - 아 래 -            \r\n \n  - [관리번호] 행2017-21001 \r\n  - [지도목적] P2P 대출시장의 건전한 발전 및 차입자와 투자자 보호\r\n  - [지도내용] 붙임 참조\r\n  - [유효기간] '20.8.27일부터 '21.8.26일까지(1년)\r\n  - [담당자] 금융감독원 핀테크혁신실\r\n  - [관련법령] 대부업 등의 등록 및 금융이용자 보호에 관한 법률\r\n  - [내부경영사항 관련] 해당 없음\r\n\n\r\n\t\t\t\t- [폐지일자] 2021년 08월 27일\r\n\t\t\t\t\t\r\n\t\t\t\t\t\r\n\t\t\t\t\n\r\n\t\t\t\t- [폐지사유] 존속기한 도래\n\n담당부서 \n\n핀테크혁신실\n\n담당팀 \n\nP2P감독팀\n\n담당자 \n\n김현진 수석검사역\n\n자료문의 \n\n02-3145-7137\n\n[첨부파일]\n- P2P대출 가이드라인_Fn_첨부용.hwp",
  "summary_text": "제목 \n\nP2P대출 가이드라인 기간 연장 및 일부 개정\n\n관리번호 \n\n행2017-21001\n\n문서번호 \n\nP2P감독팀-63\n\n시행일 \n\n20200827\n\n유효기간 \n\n\r\n\t\t\t\t\t20210827\r\n\t\t\t\t\n\n시행여부 \n\n\r\n\t\t\t\t\t\r\n\t\t\t\t\t\r\n\t\t\t\t\t폐지\r\n\t\t\t\t\t\r\n\t\t\t\t\n\n첨부파일 \n\nP2P대출 가이드라인_Fn_첨부용.hwp\n\n\r\n\t\t\t\t\r\n\t\t\t\t “이 행정지도는 금융행정의 목적을 달성하기 위하여 귀 기관에 자발적인 협조를 요청하는 것으로서, 금융당국은 이 행정지도를 준수하지 않았다는 이유만으로 귀 기관에 불이익한 조치를 하지 않습니다.”\r\n \n \n       1. 관련근거\r\n            -「금융규제 운영규정」제8조\r\n \n       2. 「온라인투자연계금융업 및 이용자 보호에 관한 법률」(이하 ‘P2P법’)이 ’20.8.27. 시행될 예정이나, 법 시행 전 P2P업을 영위하는 업체들에 대해서는 1년간 등록 유예기간이 부여되며 해당 기간 동안에는 「P2P대출 가이드라인」을 적용받게 됩니다. \r\n \n        3. 이에 따라 등록 유예기간 동안 ‘P2P법에 따라 등록한 온라인투자연계금융업자’와 ‘미등록 P2P업체’ 사이의 규제 차익이 발생할 수 있으며, 이로 인한 이용자 보호 문제 등을 감안하여 P2P법령에서 규정한 다양한 이용자 보호 장치들을 「P2P대출 가이드라인」에 포함할 필요가 있습니다. \r\n \n        4. 이에 「P2P대출 가이드라인」행정지도 내용을 개정하고 아래와 같이 가이드라인 유효기간을 ‘21.8.26.까지 추가 연장하오니, 관련업무 수행에 만전을 기하여 주시기 바랍니다.\r\n \n \n \n            - 아 래 -            \r\n \n  - [관리번호] 행2017-21001 \r\n  - [지도목적] P2P 대출시장의 건전한 발전 및 차입자와 투자자 보호\r\n  - [지도내용] 붙임 참조\r\n  - [유효기간] '20.8.27일부터 '21.8.26일까지(1년)\r\n  - [담당자] 금융감독원 핀테크혁신실\r\n  - [관련법령] 대부업 등의 등록 및 금융이용자 보호에 관한 법률\r\n  - [내부경영사항 관련] 해당 없음\r\n\n\r\n\t\t\t\t- [폐지일자] 2021년 08월 27일\r\n\t\t\t\t\t\r\n\t\t\t\t\t\r\n\t\t\t\t\n\r\n\t\t\t\t- [폐지사유] 존속기한 도래\n\n담당부서 \n\n핀테크혁신실\n\n담당팀 \n\nP2P감독팀\n\n담당자 \n\n김현진 수석검사역\n\n자료문의 \n\n02-3145-7137",
  "attachments": [
    {
      "name": "P2P대출 가이드라인_Fn_첨부용.hwp",
      "url": "https://www.fss.or.kr/fss.hpdownload?path=/law/ptl/&file=2070151_20200824162708874_0.hwp&filere=P2P%EB%8C%80%EC%B6%9C+%EA%B0%80%EC%9D%B4%EB%93%9C%EB%9D%BC%EC%9D%B8_Fn_%EC%B2%A8%EB%B6%80%EC%9A%A9.hwp",
      "ext": "hwp",
      "text": "",
      "size_bytes": 32768
    }
  ],
  "version_date": "2020-08-27",
  "related_laws": [],
  "collected_at": "2026-06-07",
  "question": "",
  "answer": "",
  "url": ""
}