{
  "doc_id": "fss_업무자료_18422",
  "source": "fss_crawler",
  "title": "기업공시 News Letter '14년 2호 게시",
  "category": "금융감독원/경영유의사항등공시",
  "doc_type": "경영유의사항등공시",
  "text": "제목: 기업공시 News Letter '14년 2호 게시\n\n기업공시 News Letter '14년 2호 게시\n\n[첨부파일]\n- 기업공시NewsLetter_제2호(2014년).pdf",
  "summary_text": "기업공시 News Letter '14년 2호 게시",
  "attachments": [
    {
      "name": "기업공시NewsLetter_제2호(2014년).pdf",
      "url": "https://www.fss.or.kr/fss/cmmn/file/fileDown.do?menuNo=200152&atchFileId=96020c7323a38a0d30d83c25645b7ea7&fileSn=1&bbsId=",
      "ext": "pdf",
      "text": "",
      "size_bytes": 258754
    }
  ],
  "version_date": "2014-02-26",
  "related_laws": [],
  "collected_at": "2026-06-07",
  "question": "",
  "answer": "",
  "url": ""
}