{
  "doc_id": "fss_업무자료_20816",
  "source": "fss_crawler",
  "title": "비중요 정보처리시스템 지정관련 FAQ",
  "category": "금융감독원/정보기술(IT)",
  "doc_type": "정보기술(IT)",
  "text": "제목: 비중요 정보처리시스템 지정관련 FAQ\n\n비중요 정보처리시스템 지정관련 FAQ를 게시하오니 업무에 참고하여 주시기 바랍니다.\n\n[첨부파일]\n- 180628_비중요 정보처리시스템 지정관련 FAQ_감독원FN_.pdf\n\n[첨부파일: 180628_비중요 정보처리시스템 지정관련 FAQ_감독원FN_.pdf]\n비중요 정보처리시스템 지정 관련 FAQ\r\n2018. 5.\r\n본 FAQ는 「전자금융감독규정」에 따른 비중요 정보처리시스템 \r\n지정을 하고자 하는 금융회사 및 전자금융업자의 업무 편의를 제고\r\n하기 위함임\r\n금융위원회\r\n금융감독원\n- 1 -\r\n1. 전자금융거래를 하지 않는 금융회사의 경우 비중요 정보처리시스템\r\n지정 관련 규정의 적용을 받지 아니하는지?\r\n□ 전자금융업무를 수행하지 않는 금융회사는 원칙적으로 비중요 정보\r\n처리시스템 지정과 관련한 전자금융감독규정(제14조의2)의 적용을\r\n받지 않습니다. ◦ 전자금융업무를 수행하는 금융회사·전자금융업자 및 전자금융\r\n거래법상 일부 회사* 등의 경우 전자금융업무 수행여부와 관계없이\r\n특정 시스템을 비중요 정보처리시스템으로 지정하고자 할 경우 \r\n비중요 정보처리시스템 지정관련 규정을 준수하여야 합니다.\r\n* 시행령 제2조 제3호, 제7호 내지 제18호에 해당하는 회사(기관) 등\r\n2. 전자금융거래와 관계없는 정보처리시스템의 경우 망분리 예외 등의\r\n적용을 받기 위해 비중요 정보처리시스템으로 지정할 필요가 있는지?\r\n□ 전자금융업무를 수행하는 금융회사·전자금융업자는 전산센터 및 \r\n본점·영업점 망분리 규정의 적용을 받으므로 이에 대한 예외를 \r\n적용받기 위해서 해당 시스템을 비중요 정보처리시스템으로 지정\r\n할 필요가 있습니다. 3. 비중요 정보처리시스템으로 지정할 수 없는 시스템의 범위는?\r\n□ 고객의 고유 식별정보 또는 신용정보가 처리되거나 이를 송·수신\r\n하거나 전달하는 시스템 등\r\n*은 비중요 정보처리시스템으로 지정하는\r\n것이 불가능합니다.\r\n* 예시) 인터넷뱅킹시스템, 증권거래시스템, 자금세탁방지시스템, 금융서비스를\r\n위한 웹서버 또는 채널시스템 등\n- 2 -\r\n◦ 다만, 고객의 고유 식별정보 또는 신용정보가 포함되어 있더라도 \r\n관련법규에 따라 비식별화 조치를 한 경우에는 비중요 정보처리\r\n시스템으로 지정이 가능합니다. 4. 고유식별정보 또는 개인신용정보에 해쉬함수를 적용하여 일방향\r\n암호화한다면 해당 정보를 처리하는 시스템을 비중요 정보처리\r\n시스템으로 지정할 수 있는지? \r\n□ 고객의 고유식별정보 또는 신용정보를 일방향 암호화 방식으로 \r\n처리 하더라도 암호화 기술수준 정도, 다른 정보와의 결합 가능성, 해당암호화 정보에 대한 접근권한 관리·통제 등을 종합적으로 고려\r\n하여 비식별화 여부 등을 판단하여야 합니다. ◦「개인정보 비식별 조치 가이드라인(’16.6.30.)」에 따라 고유식별\r\n정보 또는 신용정보에 대해 비식별화 조치를 한 경우에는 해당 \r\n시스템을 비중요 정보처리시스템으로 지정이 가능합니다.\r\n5. 클라우드 컴퓨팅 서비스를 이용하기 위해서 반드시 비중요 정보\r\n처리 시스템을 지정하여 금융감독원장에게 보고하여야 하는지?\r\n□ 전자금융거래법 및 관련 규정은 금융회사·전자금융업자의 클라\r\n우드 컴퓨팅 서비스 이용을 명시적으로 금지하지 않고 있으나, ◦ 물리적 망분리 등 일부 규정의 적용을 받지 않기 위해서는 해당 \r\n시스템을 비중요 정보처리시스템으로 지정하여 클라우드 컴퓨팅 \r\n서비스를 이용하는 것이 규정을 준수하기 용이합니다.\n- 3 -\r\n6. 고유식별정보 또는 개인신용정보가 포함되지 않은 개인정보의 처리를\r\n위하여 해당 시스템을 비중요 정보처리시스템으로 지정할 수 있는지?\r\n□ 금융회사 등은 자체 수립한 정보자산 중요도 평가기준에 따라 \r\n정보보호위원회 심의·의결을 거쳐 개인정보가 포함된 시스템을 \r\n비중요 정보처리시스템으로 지정이 가능합니다. ◦ 다만, 개인정보보호법 등 정보보호 관련법의 기술적·관리적 조치 등\r\n관련기준 준수를 전제로 평가되어 지정되어야 할 것입니다. 7. 비중요 정보처리시스템으로 지정하여 클라우드 컴퓨팅 서비스를\r\n이용할 경우 반드시 「금융회사의 정보처리 업무 위탁에 관한 \r\n규정」에 따라 정보처리 업무 위탁 보고를 하여야 하는지?\r\n□ 금융회사 등이 비중요 정보처리시스템을 지정한 경우「금융회사의 \r\n정보처리 업무 위탁에 관한 규정」제7조에 따라 정보처리 위탁에 \r\n관한 현황을 금융감독원장에게 보고하여야 합니다. 8. 비중요 정보처리시스템 지정을 위해 정보보호위원회의 심의·의결을 거친\r\n경우 심의·의결일로부터 7일 이내 금융감독원에 보고하여야 하는지?\r\n□「전자금융감독규정」제14조의2는 금융회사 등으로 하여금 비중요 \r\n정보처리시스템을 지정한 날로부터 7일 이내에 관련 보고서를 \r\n금융감독원에 제출하도록 규정하고 있습니다(동조제3항). ◦ 비중요 정보처리시스템의 지정을 위해서는 정보보호위원회의 \r\n심의·의결이 반드시 필요하지만 심의·의결 자체가 비중요 정보\r\n처리시스템의 지정행위는 아니므로 별도의 지정 행위 이후 7일 \r\n이내(영업일 기준이 아님) 금융감독원에 보고할 수 있습니다.\n- 4 -\r\n9. 회사 직원들의 인사관련 정보(연락처, 직급, 업무 등)만 처리하는 경우\r\n별도의 비식별화 조치 없이 비중요 정보처리시스템의 지정이 가능한지?\r\n□ 개인정보에 해당하는 직원의 인사정보를 처리하고자 하는 경우 원칙\r\n적으로 비식별화 조치없이 비중요 정보처리시스템 지정이 가능합니다. ◦ 다만, 직원 인사정보에 고유식별정보·신용정보 등이 포함된 경우\r\n개인정보보호법·정보통신망법·신용정보법 등에 따른 기술적·관리적\r\n조치를 전제로 비중요 정보처리시스템으로 지정되어야 합니다. 10. 비정형 데이터를 처리하는 정보처리시스템을 비중요 정보처리\r\n시스템으로 지정할 수 있는지?\r\n□ 음성정보, 이메일 등 비정형데이터를 처리하는 경우에도 비중요 \r\n정보처리시스템의 지정이 가능합니다. ◦ 다만, 비정형데이터라 하더라도 고객 고유식별정보·신용정보 \r\n등이 포함될 가능성이 있는 경우에는 해당정보가 포함되지 \r\n않도록 기술적·관리적 통제가 이루어져야 합니다. 11. 비중요 정보처리시스템의 기획/설계 단계에서도 관련절차를 \r\n거쳐 비중요 정보처리시스템 지정보고가 가능한지? \r\n□ 비중요 정보처리시스템 기획/설계 단계에서도 관련절차를 거쳐 \r\n지정결과 보고서를 금감원에 제출할 수 있습니다. ◦ 다만, 금융회사의 지정보고 이후 보고된 내용과 달리 비중요 정보\r\n처리시스템이 구현되어 운영될 경우 변경된 내용을 반영하여 \r\n비중요 정보처리시스템 지정 절차를 다시 진행하여야 합니다.\n- 5 -\r\n12. 비중요 정보처리시스템 지정결과 보고 후 구현된 비중요 정보\r\n처리시스템을 제3자에게 위탁하지 않고 내부 전산망에 두어도 \r\n문제가 없는지?\r\n□ 비중요 시스템 지정 후 제3자 위탁을 하지 않은 채(클라우드 컴퓨팅\r\n미이용) 망분리 의무 등의 적용을 배제하고 동일 전산센터 내 \r\n망분리된 시스템과 연결되어 운용될 경우 \r\n◦ 외부침해 행위로 인한 취약점이 노출될 우려가 있으므로 지정\r\n보고 내용대로 제3자에 대해 정보처리 업무를 위탁하여야 합니다. 13. 금융감독원에 비중요 정보처리시스템 지정 보고 이후 별도의 \r\n적합성 등에 대한 승인이 필요한지?\r\n□ 금융회사 등은 비중요 정보처리시스템 지정 결과를 사후 보고의 \r\n성격으로 금융감독원에 보고하므로 별도의 적합성 등에 대한 승인 \r\n절차는 없습니다. ◦ 다만, 금융회사의 평가 기준, 지정 결과, 관리 방안 등이 적절하지 \r\n않을 경우 관련 감독규정에 따라 금융감독원은 관련규정에 따라 \r\n사후적으로 이에 대한 개선·보완 요청을 받을 수 있습니다. 14. 비중요 정보처리시스템 지정 보고 이후 금융감독원장의 개선· 보완 요구 등은 언제까지 이루어지는지?\r\n□ 전자금융감독규정 제14조의2제3항에 따른 지정보고서 제출 이후 \r\n동조제4항에 따른 개선·보완 요구 등 필요한 조치는 별도 기한을 \r\n두고 있지 않습니다.\n- 6 -\r\n15. 비중요 정보처리시스템 지정과 관련 ’전자금융거래에 안전성 및 \r\n신뢰성에 미치는 영향이 현저히 낮다‘는 의미는 무엇인지?\r\n16. 비중요 정보처리시스템 지정결과 보고서 제출 시 주의할 사항은?\r\n□ 금융회사 등은 자체적으로 마련한 ‘정보자산 중요도 평가기준’을 \r\n통해 비중요 정보처리시스템 지정여부를 결정하게 되는데(전자금융\r\n감독규정 제14조의2제1항)\r\n◦ 동 기준 따라 판단하였다면 해당 시스템이 문제(해킹, 장애 등)가 \r\n발생하더라도 회사 관련업무 및 이용자에게 미치는 경제적·사회적\r\n영향이 경미해야 한다는 것을 의미합니다.\r\n□ 지정결과 보고서 제출 시 정보보호위원회 회의록 누락, 처리 데이터 \r\n세부내역 미기재, 비중요 정보처리시스템 관리방안 부실기재 등으로\r\n인해 보고내용 반려, 보완을 요청하는 사례가 다수 발생하고 있습니다. ◦ 비중요 정보처리시스템 지정결과 보고서상 필수기재 내용이 누락\r\n되지 않고 충실히 작성될 수 있도록 작성담당자는 주의를 기울\r\n일 필요가 있습니다.\n- 7 -\r\n\r\n비중요 정보처리시스템 지정 관련 규정 및 시행세칙\r\n전자금융감독규정 \r\n제14조의2(비중요 정보처리시스템 지정) ① 금융회사 또는 전자금융업자는 자체적으로\r\n수립한 정보자산 중요도 평가기준에 따라 전자금융거래의 안전성 및 신뢰성에 미치는\r\n영향이 현저히 낮은 정보처리시스템을 비중요 정보처리시스템으로 지정할 수 있다.\r\n다만, 개인의 고유식별정보 또는 「신용정보의 이용 및 보호에 관한 법률」에 따른\r\n개인신용정보를 처리하는 정보처리시스템은 비중요 정보처리시스템으로 지정할 수 없다.\r\n② 금융회사 또는 전자금융업자는 제1항에 따라 비중요 정보처리시스템 지정시 제8\r\n조의2에 따른 정보보호위원회의 심의·의결을 거쳐야 한다.\r\n③ 금융회사 또는 전자금융업자는 제1항에 따라 비중요 정보처리시스템을 지정한 날로\r\n부터 7일 이내에 금융감독원장이 정하는 양식에 따라 정보자산 중요도 평가기준, 지정\r\n결과, 관리 방안 등을 포함한 보고서를 금융감독원에 제출하여야 한다.\r\n④ 금융감독원장은 제3항에 따라 제출한 보고서를 검토한 결과, 평가 기준, 지정 결과,\r\n관리 방안 등이 적합하지 않다고 판단되는 경우에는 금융회사 또는 전자금융업자에\r\n대하여 개선·보완을 요구할 수 있다.\r\n⑤ 제1항의 비중요 정보처리시스템만 위치한 전산실에 대해서는 제11조제11호 및 제\r\n12호, 제15조제1항제5호를 적용하지 아니한다.\r\n전자금융감독규정 시행세칙 \r\n제2조의3 (비중요 정보처리시스템의 보고) 규정 제14조의2 제3항에 따라 감독원장이\r\n정하는 양식은 별지 제6호 서식에 따른다.\n- 8 -\r\n 비중요 정보처리시스템 지정결과 보고 서식\r\n작 성 자 : (직 위)\r\n전화번호 :\r\n비중요 정보처리시스템 지정결과 보고\r\n문서번호\r\n수 신\r\n참 조\r\n제 목 비중요 정보처리시스템 지정결과 보고\r\n전자금융감독규정 제 조의 제 항에 따라 붙임과 같이 비중요\r\n정보처리시스템 지정결과를 제출합니다\r\n붙 임 비중요 정보처리시스템 지정결과 보고서 부 끝\r\n　　　　\r\n○ ○ ○ ○ 대표이사 인\n- 9 -\r\n(붙임)\r\n비중요 정보처리시스템 지정결과 보고서\r\n1. 시스템명 :\r\n2. 업무 개요 : \r\n3. 업무처리 절차 \r\n※ 업무 단계별 이용자 및 데이터 흐름 표시\r\n4. 시스템 개요 \r\n가. 시스템의 용도 \r\n나. 처리 데이터\r\n다. 시스템 이용자 \r\n 라. 타 시스템과의 연계성\r\n마. 시스템 구성도 및 정보통신망 구성도\r\n5. 정보자산 중요도 평가 기준\r\n6. 비중요 정보처리시스템 지정결과\r\n별첨 : 정보보호위원회 회의록\n- 10 -\r\n7. 정보처리 업무위탁 여부\r\n위탁 여부 수탁사 위탁업무 보고 (예정)일\r\n*\r\n* 금융회사의 정보처리 업무 위탁에 관한 규정 제7조에 따름\r\n8. 비중요 정보처리시스템 관리 방안\r\n9. 시스템 책임자 \r\n소 속 직 위 이 름 담당업무 연락처 e-mail",
  "summary_text": "비중요 정보처리시스템 지정관련 FAQ를 게시하오니 업무에 참고하여 주시기 바랍니다.",
  "attachments": [
    {
      "name": "180628_비중요 정보처리시스템 지정관련 FAQ_감독원FN_.pdf",
      "url": "https://www.fss.or.kr/fss/cmmn/file/fileDown.do?menuNo=200116&atchFileId=2320c69a918554938c51a7a2d0628938&fileSn=1&bbsId=",
      "ext": "pdf",
      "text": "비중요 정보처리시스템 지정 관련 FAQ\r\n2018. 5.\r\n본 FAQ는 「전자금융감독규정」에 따른 비중요 정보처리시스템 \r\n지정을 하고자 하는 금융회사 및 전자금융업자의 업무 편의를 제고\r\n하기 위함임\r\n금융위원회\r\n금융감독원\n- 1 -\r\n1. 전자금융거래를 하지 않는 금융회사의 경우 비중요 정보처리시스템\r\n지정 관련 규정의 적용을 받지 아니하는지?\r\n□ 전자금융업무를 수행하지 않는 금융회사는 원칙적으로 비중요 정보\r\n처리시스템 지정과 관련한 전자금융감독규정(제14조의2)의 적용을\r\n받지 않습니다. ◦ 전자금융업무를 수행하는 금융회사·전자금융업자 및 전자금융\r\n거래법상 일부 회사* 등의 경우 전자금융업무 수행여부와 관계없이\r\n특정 시스템을 비중요 정보처리시스템으로 지정하고자 할 경우 \r\n비중요 정보처리시스템 지정관련 규정을 준수하여야 합니다.\r\n* 시행령 제2조 제3호, 제7호 내지 제18호에 해당하는 회사(기관) 등\r\n2. 전자금융거래와 관계없는 정보처리시스템의 경우 망분리 예외 등의\r\n적용을 받기 위해 비중요 정보처리시스템으로 지정할 필요가 있는지?\r\n□ 전자금융업무를 수행하는 금융회사·전자금융업자는 전산센터 및 \r\n본점·영업점 망분리 규정의 적용을 받으므로 이에 대한 예외를 \r\n적용받기 위해서 해당 시스템을 비중요 정보처리시스템으로 지정\r\n할 필요가 있습니다. 3. 비중요 정보처리시스템으로 지정할 수 없는 시스템의 범위는?\r\n□ 고객의 고유 식별정보 또는 신용정보가 처리되거나 이를 송·수신\r\n하거나 전달하는 시스템 등\r\n*은 비중요 정보처리시스템으로 지정하는\r\n것이 불가능합니다.\r\n* 예시) 인터넷뱅킹시스템, 증권거래시스템, 자금세탁방지시스템, 금융서비스를\r\n위한 웹서버 또는 채널시스템 등\n- 2 -\r\n◦ 다만, 고객의 고유 식별정보 또는 신용정보가 포함되어 있더라도 \r\n관련법규에 따라 비식별화 조치를 한 경우에는 비중요 정보처리\r\n시스템으로 지정이 가능합니다. 4. 고유식별정보 또는 개인신용정보에 해쉬함수를 적용하여 일방향\r\n암호화한다면 해당 정보를 처리하는 시스템을 비중요 정보처리\r\n시스템으로 지정할 수 있는지? \r\n□ 고객의 고유식별정보 또는 신용정보를 일방향 암호화 방식으로 \r\n처리 하더라도 암호화 기술수준 정도, 다른 정보와의 결합 가능성, 해당암호화 정보에 대한 접근권한 관리·통제 등을 종합적으로 고려\r\n하여 비식별화 여부 등을 판단하여야 합니다. ◦「개인정보 비식별 조치 가이드라인(’16.6.30.)」에 따라 고유식별\r\n정보 또는 신용정보에 대해 비식별화 조치를 한 경우에는 해당 \r\n시스템을 비중요 정보처리시스템으로 지정이 가능합니다.\r\n5. 클라우드 컴퓨팅 서비스를 이용하기 위해서 반드시 비중요 정보\r\n처리 시스템을 지정하여 금융감독원장에게 보고하여야 하는지?\r\n□ 전자금융거래법 및 관련 규정은 금융회사·전자금융업자의 클라\r\n우드 컴퓨팅 서비스 이용을 명시적으로 금지하지 않고 있으나, ◦ 물리적 망분리 등 일부 규정의 적용을 받지 않기 위해서는 해당 \r\n시스템을 비중요 정보처리시스템으로 지정하여 클라우드 컴퓨팅 \r\n서비스를 이용하는 것이 규정을 준수하기 용이합니다.\n- 3 -\r\n6. 고유식별정보 또는 개인신용정보가 포함되지 않은 개인정보의 처리를\r\n위하여 해당 시스템을 비중요 정보처리시스템으로 지정할 수 있는지?\r\n□ 금융회사 등은 자체 수립한 정보자산 중요도 평가기준에 따라 \r\n정보보호위원회 심의·의결을 거쳐 개인정보가 포함된 시스템을 \r\n비중요 정보처리시스템으로 지정이 가능합니다. ◦ 다만, 개인정보보호법 등 정보보호 관련법의 기술적·관리적 조치 등\r\n관련기준 준수를 전제로 평가되어 지정되어야 할 것입니다. 7. 비중요 정보처리시스템으로 지정하여 클라우드 컴퓨팅 서비스를\r\n이용할 경우 반드시 「금융회사의 정보처리 업무 위탁에 관한 \r\n규정」에 따라 정보처리 업무 위탁 보고를 하여야 하는지?\r\n□ 금융회사 등이 비중요 정보처리시스템을 지정한 경우「금융회사의 \r\n정보처리 업무 위탁에 관한 규정」제7조에 따라 정보처리 위탁에 \r\n관한 현황을 금융감독원장에게 보고하여야 합니다. 8. 비중요 정보처리시스템 지정을 위해 정보보호위원회의 심의·의결을 거친\r\n경우 심의·의결일로부터 7일 이내 금융감독원에 보고하여야 하는지?\r\n□「전자금융감독규정」제14조의2는 금융회사 등으로 하여금 비중요 \r\n정보처리시스템을 지정한 날로부터 7일 이내에 관련 보고서를 \r\n금융감독원에 제출하도록 규정하고 있습니다(동조제3항). ◦ 비중요 정보처리시스템의 지정을 위해서는 정보보호위원회의 \r\n심의·의결이 반드시 필요하지만 심의·의결 자체가 비중요 정보\r\n처리시스템의 지정행위는 아니므로 별도의 지정 행위 이후 7일 \r\n이내(영업일 기준이 아님) 금융감독원에 보고할 수 있습니다.\n- 4 -\r\n9. 회사 직원들의 인사관련 정보(연락처, 직급, 업무 등)만 처리하는 경우\r\n별도의 비식별화 조치 없이 비중요 정보처리시스템의 지정이 가능한지?\r\n□ 개인정보에 해당하는 직원의 인사정보를 처리하고자 하는 경우 원칙\r\n적으로 비식별화 조치없이 비중요 정보처리시스템 지정이 가능합니다. ◦ 다만, 직원 인사정보에 고유식별정보·신용정보 등이 포함된 경우\r\n개인정보보호법·정보통신망법·신용정보법 등에 따른 기술적·관리적\r\n조치를 전제로 비중요 정보처리시스템으로 지정되어야 합니다. 10. 비정형 데이터를 처리하는 정보처리시스템을 비중요 정보처리\r\n시스템으로 지정할 수 있는지?\r\n□ 음성정보, 이메일 등 비정형데이터를 처리하는 경우에도 비중요 \r\n정보처리시스템의 지정이 가능합니다. ◦ 다만, 비정형데이터라 하더라도 고객 고유식별정보·신용정보 \r\n등이 포함될 가능성이 있는 경우에는 해당정보가 포함되지 \r\n않도록 기술적·관리적 통제가 이루어져야 합니다. 11. 비중요 정보처리시스템의 기획/설계 단계에서도 관련절차를 \r\n거쳐 비중요 정보처리시스템 지정보고가 가능한지? \r\n□ 비중요 정보처리시스템 기획/설계 단계에서도 관련절차를 거쳐 \r\n지정결과 보고서를 금감원에 제출할 수 있습니다. ◦ 다만, 금융회사의 지정보고 이후 보고된 내용과 달리 비중요 정보\r\n처리시스템이 구현되어 운영될 경우 변경된 내용을 반영하여 \r\n비중요 정보처리시스템 지정 절차를 다시 진행하여야 합니다.\n- 5 -\r\n12. 비중요 정보처리시스템 지정결과 보고 후 구현된 비중요 정보\r\n처리시스템을 제3자에게 위탁하지 않고 내부 전산망에 두어도 \r\n문제가 없는지?\r\n□ 비중요 시스템 지정 후 제3자 위탁을 하지 않은 채(클라우드 컴퓨팅\r\n미이용) 망분리 의무 등의 적용을 배제하고 동일 전산센터 내 \r\n망분리된 시스템과 연결되어 운용될 경우 \r\n◦ 외부침해 행위로 인한 취약점이 노출될 우려가 있으므로 지정\r\n보고 내용대로 제3자에 대해 정보처리 업무를 위탁하여야 합니다. 13. 금융감독원에 비중요 정보처리시스템 지정 보고 이후 별도의 \r\n적합성 등에 대한 승인이 필요한지?\r\n□ 금융회사 등은 비중요 정보처리시스템 지정 결과를 사후 보고의 \r\n성격으로 금융감독원에 보고하므로 별도의 적합성 등에 대한 승인 \r\n절차는 없습니다. ◦ 다만, 금융회사의 평가 기준, 지정 결과, 관리 방안 등이 적절하지 \r\n않을 경우 관련 감독규정에 따라 금융감독원은 관련규정에 따라 \r\n사후적으로 이에 대한 개선·보완 요청을 받을 수 있습니다. 14. 비중요 정보처리시스템 지정 보고 이후 금융감독원장의 개선· 보완 요구 등은 언제까지 이루어지는지?\r\n□ 전자금융감독규정 제14조의2제3항에 따른 지정보고서 제출 이후 \r\n동조제4항에 따른 개선·보완 요구 등 필요한 조치는 별도 기한을 \r\n두고 있지 않습니다.\n- 6 -\r\n15. 비중요 정보처리시스템 지정과 관련 ’전자금융거래에 안전성 및 \r\n신뢰성에 미치는 영향이 현저히 낮다‘는 의미는 무엇인지?\r\n16. 비중요 정보처리시스템 지정결과 보고서 제출 시 주의할 사항은?\r\n□ 금융회사 등은 자체적으로 마련한 ‘정보자산 중요도 평가기준’을 \r\n통해 비중요 정보처리시스템 지정여부를 결정하게 되는데(전자금융\r\n감독규정 제14조의2제1항)\r\n◦ 동 기준 따라 판단하였다면 해당 시스템이 문제(해킹, 장애 등)가 \r\n발생하더라도 회사 관련업무 및 이용자에게 미치는 경제적·사회적\r\n영향이 경미해야 한다는 것을 의미합니다.\r\n□ 지정결과 보고서 제출 시 정보보호위원회 회의록 누락, 처리 데이터 \r\n세부내역 미기재, 비중요 정보처리시스템 관리방안 부실기재 등으로\r\n인해 보고내용 반려, 보완을 요청하는 사례가 다수 발생하고 있습니다. ◦ 비중요 정보처리시스템 지정결과 보고서상 필수기재 내용이 누락\r\n되지 않고 충실히 작성될 수 있도록 작성담당자는 주의를 기울\r\n일 필요가 있습니다.\n- 7 -\r\n\r\n비중요 정보처리시스템 지정 관련 규정 및 시행세칙\r\n전자금융감독규정 \r\n제14조의2(비중요 정보처리시스템 지정) ① 금융회사 또는 전자금융업자는 자체적으로\r\n수립한 정보자산 중요도 평가기준에 따라 전자금융거래의 안전성 및 신뢰성에 미치는\r\n영향이 현저히 낮은 정보처리시스템을 비중요 정보처리시스템으로 지정할 수 있다.\r\n다만, 개인의 고유식별정보 또는 「신용정보의 이용 및 보호에 관한 법률」에 따른\r\n개인신용정보를 처리하는 정보처리시스템은 비중요 정보처리시스템으로 지정할 수 없다.\r\n② 금융회사 또는 전자금융업자는 제1항에 따라 비중요 정보처리시스템 지정시 제8\r\n조의2에 따른 정보보호위원회의 심의·의결을 거쳐야 한다.\r\n③ 금융회사 또는 전자금융업자는 제1항에 따라 비중요 정보처리시스템을 지정한 날로\r\n부터 7일 이내에 금융감독원장이 정하는 양식에 따라 정보자산 중요도 평가기준, 지정\r\n결과, 관리 방안 등을 포함한 보고서를 금융감독원에 제출하여야 한다.\r\n④ 금융감독원장은 제3항에 따라 제출한 보고서를 검토한 결과, 평가 기준, 지정 결과,\r\n관리 방안 등이 적합하지 않다고 판단되는 경우에는 금융회사 또는 전자금융업자에\r\n대하여 개선·보완을 요구할 수 있다.\r\n⑤ 제1항의 비중요 정보처리시스템만 위치한 전산실에 대해서는 제11조제11호 및 제\r\n12호, 제15조제1항제5호를 적용하지 아니한다.\r\n전자금융감독규정 시행세칙 \r\n제2조의3 (비중요 정보처리시스템의 보고) 규정 제14조의2 제3항에 따라 감독원장이\r\n정하는 양식은 별지 제6호 서식에 따른다.\n- 8 -\r\n 비중요 정보처리시스템 지정결과 보고 서식\r\n작 성 자 : (직 위)\r\n전화번호 :\r\n비중요 정보처리시스템 지정결과 보고\r\n문서번호\r\n수 신\r\n참 조\r\n제 목 비중요 정보처리시스템 지정결과 보고\r\n전자금융감독규정 제 조의 제 항에 따라 붙임과 같이 비중요\r\n정보처리시스템 지정결과를 제출합니다\r\n붙 임 비중요 정보처리시스템 지정결과 보고서 부 끝\r\n　　　　\r\n○ ○ ○ ○ 대표이사 인\n- 9 -\r\n(붙임)\r\n비중요 정보처리시스템 지정결과 보고서\r\n1. 시스템명 :\r\n2. 업무 개요 : \r\n3. 업무처리 절차 \r\n※ 업무 단계별 이용자 및 데이터 흐름 표시\r\n4. 시스템 개요 \r\n가. 시스템의 용도 \r\n나. 처리 데이터\r\n다. 시스템 이용자 \r\n 라. 타 시스템과의 연계성\r\n마. 시스템 구성도 및 정보통신망 구성도\r\n5. 정보자산 중요도 평가 기준\r\n6. 비중요 정보처리시스템 지정결과\r\n별첨 : 정보보호위원회 회의록\n- 10 -\r\n7. 정보처리 업무위탁 여부\r\n위탁 여부 수탁사 위탁업무 보고 (예정)일\r\n*\r\n* 금융회사의 정보처리 업무 위탁에 관한 규정 제7조에 따름\r\n8. 비중요 정보처리시스템 관리 방안\r\n9. 시스템 책임자 \r\n소 속 직 위 이 름 담당업무 연락처 e-mail",
      "size_bytes": 508675
    }
  ],
  "version_date": "2018-05-18",
  "related_laws": [],
  "collected_at": "2026-06-07",
  "question": "",
  "answer": "",
  "url": ""
}